odoo/addons/stock_reception_screen_measuring_device/README.rst
odoo/addons/stock_reception_screen_measuring_device/__init__.py
odoo/addons/stock_reception_screen_measuring_device/__manifest__.py
odoo/addons/stock_reception_screen_measuring_device/i18n/es_AR.po
odoo/addons/stock_reception_screen_measuring_device/i18n/it.po
odoo/addons/stock_reception_screen_measuring_device/i18n/pt_BR.po
odoo/addons/stock_reception_screen_measuring_device/i18n/stock_reception_screen_measuring_device.pot
odoo/addons/stock_reception_screen_measuring_device/migrations/14.0.2.0.0/post-migration.py
odoo/addons/stock_reception_screen_measuring_device/migrations/14.0.2.0.0/pre-migration.py
odoo/addons/stock_reception_screen_measuring_device/models/__init__.py
odoo/addons/stock_reception_screen_measuring_device/models/measuring_device.py
odoo/addons/stock_reception_screen_measuring_device/models/stock_reception_screen.py
odoo/addons/stock_reception_screen_measuring_device/readme/CONTRIBUTORS.rst
odoo/addons/stock_reception_screen_measuring_device/readme/CREDITS.rst
odoo/addons/stock_reception_screen_measuring_device/readme/DESCRIPTION.rst
odoo/addons/stock_reception_screen_measuring_device/readme/USAGE.rst
odoo/addons/stock_reception_screen_measuring_device/static/description/icon.png
odoo/addons/stock_reception_screen_measuring_device/static/description/index.html
odoo/addons/stock_reception_screen_measuring_device/tests/__init__.py
odoo/addons/stock_reception_screen_measuring_device/tests/fake_components.py
odoo/addons/stock_reception_screen_measuring_device/tests/fake_models.py
odoo/addons/stock_reception_screen_measuring_device/tests/test_reception_screen_measurement.py
odoo/addons/stock_reception_screen_measuring_device/views/measuring_device_view.xml
odoo/addons/stock_reception_screen_measuring_device/views/stock_reception_screen_view.xml
odoo14_addon_stock_reception_screen_measuring_device-14.0.2.0.1.dev5.dist-info/METADATA
odoo14_addon_stock_reception_screen_measuring_device-14.0.2.0.1.dev5.dist-info/WHEEL
odoo14_addon_stock_reception_screen_measuring_device-14.0.2.0.1.dev5.dist-info/top_level.txt
odoo14_addon_stock_reception_screen_measuring_device-14.0.2.0.1.dev5.dist-info/RECORD
