Metadata-Version: 2.1
Name: odoo14-addon-stock_reception_screen_measuring_device
Version: 14.0.2.0.1.dev5
Summary: Allow to use a measuring device from a reception screen.for packaging measurement
Home-page: https://github.com/OCA/wms
Author: Camptocamp, Odoo Community Association (OCA)
Author-email: support@odoo-community.org
License: AGPL-3
Classifier: Programming Language :: Python
Classifier: Framework :: Odoo
Classifier: Framework :: Odoo :: 14.0
Classifier: License :: OSI Approved :: GNU Affero General Public License v3
Classifier: Development Status :: 3 - Alpha
Requires-Python: >=3.6
Requires-Dist: odoo14-addon-stock-measuring-device
Requires-Dist: odoo14-addon-stock-reception-screen
Requires-Dist: odoo<14.1dev,>=14.0a
